streamlit_downloader/__init__.py
streamlit_downloader/example.py
streamlit_downloader/frontend/build/bootstrap.min.css
streamlit_downloader/frontend/build/index.html
streamlit_downloader/frontend/build/assets/index-Z0fEwOzC.js
streamlit_downloader-0.0.3.dist-info/licenses/LICENSE
streamlit_downloader-0.0.3.dist-info/METADATA
streamlit_downloader-0.0.3.dist-info/WHEEL
streamlit_downloader-0.0.3.dist-info/top_level.txt
streamlit_downloader-0.0.3.dist-info/RECORD
